yuuno/__init__.py
yuuno/audio.py
yuuno/autodiscover.py
yuuno/clip.py
yuuno/console_scripts.py
yuuno/standalone.py
yuuno/trait_types.py
yuuno/utils.py
yuuno/yuuno.py
yuuno/core/__init__.py
yuuno/core/environment.py
yuuno/core/extension.py
yuuno/core/namespace.py
yuuno/core/registry.py
yuuno/core/settings.py
yuuno/multi_scripts/__init__.py
yuuno/multi_scripts/environments.py
yuuno/multi_scripts/extension.py
yuuno/multi_scripts/script.py
yuuno/multi_scripts/utils.py
yuuno/multi_scripts/os/__init__.py
yuuno/multi_scripts/os/unix.py
yuuno/multi_scripts/os/win32.py
yuuno/multi_scripts/subprocess/__init__.py
yuuno/multi_scripts/subprocess/basic_commands.py
yuuno/multi_scripts/subprocess/clip.py
yuuno/multi_scripts/subprocess/manager.py
yuuno/multi_scripts/subprocess/process.py
yuuno/multi_scripts/subprocess/provider.py
yuuno/multi_scripts/subprocess/proxy.py
yuuno/output/__init__.py
yuuno/output/pil2png.py
yuuno/output/srgb_png.py
yuuno/vs/__init__.py
yuuno/vs/alpha.py
yuuno/vs/audioop.py
yuuno/vs/clip.py
yuuno/vs/extension.py
yuuno/vs/flags.py
yuuno/vs/provider.py
yuuno/vs/utils.py
yuuno/vs/policy/__init__.py
yuuno/vs/policy/clip.py
yuuno/vs/policy/environment.py
yuuno/vs/vsscript/__init__.py
yuuno/vs/vsscript/capsules.py
yuuno/vs/vsscript/clip.py
yuuno/vs/vsscript/containermodule.py
yuuno/vs/vsscript/script.py
yuuno/vs/vsscript/vs_capi.py
yuuno-1.4.data/data/etc/jupyter/nbconfig/notebook.d/yuuno-jupyter.json
yuuno-1.4.data/data/share/jupyter/labextensions/@yuuno/jupyterlab/build_log.json
yuuno-1.4.data/data/share/jupyter/labextensions/@yuuno/jupyterlab/install.json
yuuno-1.4.data/data/share/jupyter/labextensions/@yuuno/jupyterlab/package.json
yuuno-1.4.data/data/share/jupyter/labextensions/@yuuno/jupyterlab/third-party-licenses.json
yuuno-1.4.data/data/share/jupyter/labextensions/@yuuno/jupyterlab/schemas/@yuuno/jupyterlab/package.json.orig
yuuno-1.4.data/data/share/jupyter/labextensions/@yuuno/jupyterlab/schemas/@yuuno/jupyterlab/plugin.json
yuuno-1.4.dist-info/AUTHORS.rst
yuuno-1.4.dist-info/COPYING
yuuno-1.4.dist-info/COPYING.EXCEPTIONS
yuuno-1.4.dist-info/METADATA
yuuno-1.4.dist-info/WHEEL
yuuno-1.4.dist-info/entry_points.txt
yuuno-1.4.dist-info/top_level.txt
yuuno-1.4.dist-info/RECORD
