Metadata-Version: 2.1
Name: yuuno
Version: 1.4
Summary: Yuuno = Jupyter + VapourSynth
Home-page: https://github.com/Irrational-Encoding-Wizardry/yuuno
Author: cid-chan
Author-email: cid+yuuno@cid-chan.moe
License: GNU Affero General Public License v3 (AGPLv3)
Keywords: yuuno
Platform: UNKNOWN
Classifier: Natural Language :: English
Classifier: Development Status :: 5 - Production/Stable
Classifier: Intended Audience :: Developers
Classifier: Intended Audience :: Other Audience
Classifier: License :: OSI Approved :: GNU Affero General Public License v3
Classifier: Programming Language :: Python :: 3.9
Classifier: Framework :: Jupyter
Classifier: Framework :: Jupyter :: JupyterLab
Classifier: Framework :: Jupyter :: JupyterLab :: 3
Classifier: Framework :: Jupyter :: JupyterLab :: Extensions
Classifier: Framework :: Jupyter :: JupyterLab :: Extensions :: Prebuilt
Classifier: Topic :: Multimedia :: Video
Classifier: Topic :: Multimedia :: Video :: Display
Classifier: Topic :: Multimedia :: Video :: Non-Linear Editor
License-File: COPYING
License-File: COPYING.EXCEPTIONS
License-File: AUTHORS.rst
Requires-Dist: jupyter
Requires-Dist: jupyterlab
Requires-Dist: traitlets
Requires-Dist: jinja2
Requires-Dist: ipywidgets
Requires-Dist: pillow
Requires-Dist: psutil
